suponoff-0.1.data/scripts/suponoff-monhelper.py
suponoff-0.1.dist-info/METADATA
suponoff-0.1.dist-info/WHEEL
suponoff-0.1.dist-info/metadata.json
suponoff-0.1.dist-info/RECORD
suponoff-0.1.dist-info/DESCRIPTION.rst
suponoff-0.1.dist-info/top_level.txt
suponoff/views.py
suponoff/urls.py
suponoff/__init__.py
suponoff/templatetags/__init__.py
suponoff/templatetags/suponoff.py
suponoff/templates/suponoff/index.html
suponoff/static/suponoff/suponoff.js
suponoff/static/suponoff/ajax-loader.gif
